{
    "hotels": [
        {
          "name" : "Le Indochina Hotel",
          "phone" : "0911488819"
        }
    ],
    "friends": [
        {
            "name": "Duy",
            "phone": "0393718247"
        },
        {
            "name": "Trang",
            "phone": "0389441863"
        },
        {
            "name": "Phương Anh",
            "phone": "0327623577"
        },
        {
            "name": "Hà",
            "phone": "0989984776"
        },
        {
            "name": "Trà",
            "phone": "0976058754"
        },
        {
            "name": "Việt Anh",
            "phone": "0349112082"
        },
        {
            "name": "Duyên",
            "phone": "0965610198"
        }
    ],
    "restaurants": [
    ],
    "emergency": [
        {
            "name": "Công an thành phố",
            "phone": "05113822300"
        },
        {
            "name": "Công an thành phố 2",
            "phone": "05113113"
        },
        {
            "name": "Cấp cứu",
            "phone": "05113114"
        },
        {
            "name": "Trung tâm tư vấn hỗ trợ du khách của thành phố Đà Nẵng",
            "phone": "05113550111"
        }
    ]
}